MANIFEST.in
README.md
setup.py
BotBot.egg-info/PKG-INFO
BotBot.egg-info/SOURCES.txt
BotBot.egg-info/dependency_links.txt
BotBot.egg-info/entry_points.txt
BotBot.egg-info/requires.txt
BotBot.egg-info/top_level.txt
botbot/__init__.py
botbot/botbot.py
botbot/checker.py
botbot/checks.py
botbot/config.py
botbot/fileinfo.py
botbot/ignore.py
botbot/problems.py
botbot/report.py
botbot/schecks.py
botbot/sqlcache.py
botbot/resources/botbot.conf
botbot/resources/templates/generic.txt