Metadata-Version: 1.0
Name: BotBot
Version: 0.1.1
Summary: Laboratory computational resource management
Home-page: http://github.com/jackstanek/BotBot
Author: Jack Stanek
Author-email: stane064@umn.edu
License: UNKNOWN
Platform: UNKNOWN
